odoo/addons/project_forecast_line_priority/README.rst
odoo/addons/project_forecast_line_priority/__init__.py
odoo/addons/project_forecast_line_priority/__manifest__.py
odoo/addons/project_forecast_line_priority/data/ir_actions_server.xml
odoo/addons/project_forecast_line_priority/i18n/it.po
odoo/addons/project_forecast_line_priority/i18n/project_forecast_line_priority.pot
odoo/addons/project_forecast_line_priority/models/__init__.py
odoo/addons/project_forecast_line_priority/models/project_task.py
odoo/addons/project_forecast_line_priority/models/res_company.py
odoo/addons/project_forecast_line_priority/models/res_config_settings.py
odoo/addons/project_forecast_line_priority/readme/CONTRIBUTORS.rst
odoo/addons/project_forecast_line_priority/readme/DESCRIPTION.rst
odoo/addons/project_forecast_line_priority/static/description/icon.png
odoo/addons/project_forecast_line_priority/static/description/index.html
odoo/addons/project_forecast_line_priority/tests/__init__.py
odoo/addons/project_forecast_line_priority/tests/test_forecast_line_priority.py
odoo/addons/project_forecast_line_priority/views/res_config_settings.xml
odoo14_addon_project_forecast_line_priority-14.0.1.0.1.dist-info/METADATA
odoo14_addon_project_forecast_line_priority-14.0.1.0.1.dist-info/WHEEL
odoo14_addon_project_forecast_line_priority-14.0.1.0.1.dist-info/top_level.txt
odoo14_addon_project_forecast_line_priority-14.0.1.0.1.dist-info/RECORD
