Metadata-Version: 2.1
Name: odoo14-addon-project_forecast_line_priority
Version: 14.0.1.0.1
Summary: Project Forecast Line dates according to task priority
Home-page: https://github.com/OCA/project
Author: Therp BV, Odoo Community Association (OCA)
Author-email: support@odoo-community.org
License: AGPL-3
Classifier: Programming Language :: Python
Classifier: Framework :: Odoo
Classifier: Framework :: Odoo :: 14.0
Classifier: License :: OSI Approved :: GNU Affero General Public License v3
Classifier: Development Status :: 3 - Alpha
Requires-Python: >=3.6
Requires-Dist: odoo14-addon-project-forecast-line-deadline
Requires-Dist: odoo14-addon-project-task-add-very-high
Requires-Dist: odoo <14.1dev,>=14.0a
